ssd1306_oled/__init__.py
ssd1306_oled/modules/__init__.py
ssd1306_oled/modules/oled/__init__.py
ssd1306_oled/modules/oled/board.py
ssd1306_oled/modules/oled/busio.py
ssd1306_oled/modules/oled/chip.py
ssd1306_oled/modules/oled/digitalio.py
ssd1306_oled/modules/oled/framebuf.py
ssd1306_oled/modules/oled/pure_spi.py
ssd1306_oled/modules/oled/spi.py
ssd1306_oled/modules/oled/spi_device.py
ssd1306_oled/modules/oled/ssd1306.py
ssd1306_oled/modules/oled/util.py
ssd1306_oled-0.1.1.dist-info/METADATA
ssd1306_oled-0.1.1.dist-info/WHEEL
ssd1306_oled-0.1.1.dist-info/top_level.txt
ssd1306_oled-0.1.1.dist-info/RECORD
