Metadata-Version: 2.1
Name: ssd1306-oled
Version: 0.1.1
Summary: ssd1306 package.
Home-page: https://github.com/leeyunjai/ssd1306-oled
Author: leeyunjai
Author-email: leeyunjai1982@gmail.com
License: UNKNOWN
Keywords: ssd1306-oled
Platform: UNKNOWN
Classifier: Natural Language :: English
Classifier: Programming Language :: Python :: 3.5
Classifier: Programming Language :: Python :: 3.6
Classifier: Programming Language :: Python :: 3.7
Classifier: Programming Language :: Python :: 3.8
Classifier: Programming Language :: Python :: 3.9
Requires-Dist: pillow (>=7.2.0)
